flask_mailing/__init__.py
flask_mailing/config.py
flask_mailing/connection.py
flask_mailing/errors.py
flask_mailing/mail.py
flask_mailing/msg.py
flask_mailing/schemas.py
flask_mailing/utils/__init__.py
flask_mailing/utils/email_check.py
flask_mailing/utils/errors.py
Flask_Mailing-0.2.3.dist-info/LICENSE
Flask_Mailing-0.2.3.dist-info/METADATA
Flask_Mailing-0.2.3.dist-info/WHEEL
Flask_Mailing-0.2.3.dist-info/top_level.txt
Flask_Mailing-0.2.3.dist-info/RECORD
