Metadata-Version: 2.1
Name: Flask-Mailing
Version: 0.2.3
Summary: Flask mail system sending mails(individual, bulk) attachments(individual, bulk) fully asynchroniously
Home-page: https://github.com/marktennyson/flask-mailing
Author: Aniket Sarkar
Author-email: aniketsarkar@yahoo.com
License: MIT
Keywords: flask,flask-mail,flask-mailing,async-flask,asynchroniously-send-email-in-flask,async-mailer,flask-email,flask-mailman
Platform: any
Classifier: Development Status :: 5 - Production/Stable
Classifier: Environment :: Web Environment
Classifier: Framework :: Flask
Classifier: Intended Audience :: Developers
Classifier: License :: OSI Approved :: MIT License
Classifier: Operating System :: OS Independent
Classifier: Programming Language :: Python
Classifier: Programming Language :: Python :: 3
Classifier: Programming Language :: Python :: 3 :: Only
Classifier: Programming Language :: Python :: 3.6
Classifier: Programming Language :: Python :: 3.7
Classifier: Programming Language :: Python :: 3.8
Classifier: Programming Language :: Python :: 3.9
Classifier: Programming Language :: Python :: 3.10
Classifier: Programming Language :: Python :: 3.11
Classifier: Programming Language :: Python :: Implementation :: CPython
Classifier: Programming Language :: Python :: Implementation :: PyPy
Classifier: Topic :: Software Development :: Libraries :: Python Modules
Requires-Python: >=3.6,<4
License-File: LICENSE
Requires-Dist: aiosmtplib>=1.1.6
Requires-Dist: aioredis>=2.0.0
Requires-Dist: asgiref>=3.4.1
Requires-Dist: blinker>=1.4
Requires-Dist: pydantic>=1.8.2
Requires-Dist: pydantic-settings>=2.0.3
Requires-Dist: email-validator>=1.1.3
Requires-Dist: typing-extensions>=3.10.0.0
Requires-Dist: httpx>=0.21.3
Requires-Dist: flask>=2.0.0
